pyparser/__init__.py
atro_pyparser-0.0.2.dist-info/METADATA
atro_pyparser-0.0.2.dist-info/WHEEL
atro_pyparser-0.0.2.dist-info/top_level.txt
atro_pyparser-0.0.2.dist-info/RECORD
