Metadata-Version: 2.1
Name: atro-pyparser
Version: 0.0.2
Summary: A simple parsing wrapper around argparse. It works with atro-pylog otherwise its just about the same.
Home-page: https://github.com/atropos/atro-pylog
Author: Atropos
Author-email: pypi.rising@atro.xyz
Classifier: License :: OSI Approved :: MIT License
Classifier: Programming Language :: Python
Classifier: Programming Language :: Python :: 3
Classifier: Programming Language :: Python :: 3.6
Classifier: Programming Language :: Python :: 3.7
Classifier: Programming Language :: Python :: 3.8
Classifier: Programming Language :: Python :: 3.9
Classifier: Programming Language :: Python :: 3.10
Classifier: Programming Language :: Python :: 3.11
Requires-Dist: atro-pylog
Requires-Dist: argparse
